snp500.py
SNP500-0.1.dist-info/METADATA
SNP500-0.1.dist-info/WHEEL
SNP500-0.1.dist-info/top_level.txt
SNP500-0.1.dist-info/RECORD
