Metadata-Version: 2.1
Name: SNP500
Version: 0.1
Summary: Fetch S&P 500 tickers from Wikipedia
Home-page: UNKNOWN
Author: Aung Si
Author-email: aungsi.as99@gmail.com
License: UNKNOWN
Platform: UNKNOWN
Requires-Dist: pandas
